uutil/__init__.py
uutil/case.py
uutil/excel.py
uutil-0.0.5.dist-info/LICENSE
uutil-0.0.5.dist-info/METADATA
uutil-0.0.5.dist-info/WHEEL
uutil-0.0.5.dist-info/top_level.txt
uutil-0.0.5.dist-info/RECORD
