Metadata-Version: 2.1
Name: uutil
Version: 0.0.5
Summary: useful utils
Home-page: https://github.com/kerol/uutil
Author: kerol
Author-email: ikerol@163.com
License: The MIT License (MIT)
Keywords: office word ppt excel
Classifier: Development Status :: 3 - Alpha
Classifier: Environment :: Console
Classifier: Intended Audience :: Developers
Classifier: License :: OSI Approved :: MIT License
Classifier: Operating System :: OS Independent
Classifier: Programming Language :: Python
Classifier: Programming Language :: Python :: 3
Classifier: Programming Language :: Python :: 3.3
Classifier: Programming Language :: Python :: 3.4
Classifier: Topic :: Office/Business :: Office Suites
Classifier: Topic :: Software Development :: Libraries
License-File: LICENSE
Requires-Dist: lxml >=2.3.2
